aind_exaspim_pipeline_utils/__init__.py
aind_exaspim_pipeline_utils/exaspim_manifest.py
aind_exaspim_pipeline_utils/imagej_macros.py
aind_exaspim_pipeline_utils/imagej_wrapper.py
aind_exaspim_pipeline_utils/java_utils.py
aind_exaspim_pipeline_utils/n5tozarr/__init__.py
aind_exaspim_pipeline_utils/n5tozarr/n5tozarr_da.py
aind_exaspim_pipeline_utils/qc/__init__.py
aind_exaspim_pipeline_utils/qc/affine_transformation.py
aind_exaspim_pipeline_utils/qc/bbox.py
aind_exaspim_pipeline_utils/qc/bigstitcher_log_edge_analysis.py
aind_exaspim_pipeline_utils/qc/create_ng_link.py
aind_exaspim_pipeline_utils/qc/image_cutout.py
aind_exaspim_pipeline_utils/qc/ip_density.py
aind_exaspim_pipeline_utils/qc/ng_ip_visualization.py
aind_exaspim_pipeline_utils/qc/tile_transformations.py
aind_exaspim_pipeline_utils/trigger/__init__.py
aind_exaspim_pipeline_utils/trigger/capsule.py
aind_trigger_codeocean/__init__.py
aind_trigger_codeocean/pipelines.py
aind_exaspim_pipeline_utils-0.11.2.dist-info/LICENSE
aind_exaspim_pipeline_utils-0.11.2.dist-info/METADATA
aind_exaspim_pipeline_utils-0.11.2.dist-info/WHEEL
aind_exaspim_pipeline_utils-0.11.2.dist-info/entry_points.txt
aind_exaspim_pipeline_utils-0.11.2.dist-info/top_level.txt
aind_exaspim_pipeline_utils-0.11.2.dist-info/RECORD
