Metadata-Version: 2.1
Name: aind_exaspim_pipeline_utils
Version: 0.11.2
Summary: AIND exaSPIM pipeline utilities.
Author: Allen Institute for Neural Dynamics
License: MIT
Classifier: Programming Language :: Python :: 3
Requires-Python: >=3.8
License-File: LICENSE
Requires-Dist: argschema
Requires-Dist: s3fs
Requires-Dist: pydantic
Requires-Dist: psutil
Requires-Dist: matplotlib
Requires-Dist: scipy
Requires-Dist: aind-data-schema ==0.33.3
Requires-Dist: aind-codeocean-api
Requires-Dist: aind-ng-link >=1.0.15
Requires-Dist: numpy <2.0
Provides-Extra: dev
Requires-Dist: aind-exaspim-pipeline-utils[n5tozarr] ; extra == 'dev'
Requires-Dist: black ; extra == 'dev'
Requires-Dist: coverage ; extra == 'dev'
Requires-Dist: flake8 ; extra == 'dev'
Requires-Dist: interrogate ; extra == 'dev'
Requires-Dist: isort ; extra == 'dev'
Requires-Dist: Sphinx ; extra == 'dev'
Requires-Dist: furo ; extra == 'dev'
Provides-Extra: n5tozarr
Requires-Dist: dask ; extra == 'n5tozarr'
Requires-Dist: distributed ; extra == 'n5tozarr'
Requires-Dist: zarr ; extra == 'n5tozarr'
Requires-Dist: numcodecs ; extra == 'n5tozarr'
Requires-Dist: aind-data-transfer[imaging] ==0.35.3 ; extra == 'n5tozarr'
Requires-Dist: hdf5plugin ; extra == 'n5tozarr'
Requires-Dist: kerchunk ; extra == 'n5tozarr'
